connattractor/__init__.py
connattractor/analysis.py
connattractor/config.py
connattractor/network.py
connattractor/statedynamics.py
connattractor/utils.py
resources/MIST122_relabeled.nii.gz
resources/MIST122_relabeled.tsv
resources/__init__.py
resources/connectome_partial_correlation.csv
resources/default_hopfield_embedding_0.37.pkl
resources/ex_timeseries_task/_calculate_FD_Power32.txt
resources/ex_timeseries_task/_extract_timeseries32.tsv
resources/ex_timeseries_task/sub-01_FD_run_03.txt
resources/ex_timeseries_task/sub-01_FD_run_07.txt
resources/ex_timeseries_task/sub-01_task-heatpainwithregulationandratings_run-01_events.tsv
resources/ex_timeseries_task/sub-01_task-heatpainwithregulationandratings_run-03_events.tsv
resources/ex_timeseries_task/sub-01_task-heatpainwithregulationandratings_run-07_events.tsv
resources/ex_timeseries_task/sub-01_ts_run_03.tsv
resources/ex_timeseries_task/sub-01_ts_run_07.tsv
resources/ex_timeseries_task/sub-02_FD.txt
resources/ex_timeseries_task/sub-02_FD_run_03.txt
resources/ex_timeseries_task/sub-02_FD_run_07.txt
resources/ex_timeseries_task/sub-02_task-heatpainwithregulationandratings_run-01_events.tsv
resources/ex_timeseries_task/sub-02_task-heatpainwithregulationandratings_run-03_events.tsv
resources/ex_timeseries_task/sub-02_task-heatpainwithregulationandratings_run-07_events.tsv
resources/ex_timeseries_task/sub-02_ts.txt
resources/ex_timeseries_task/sub-02_ts_run_03.tsv
resources/ex_timeseries_task/sub-02_ts_run_07.tsv
resources/ex_timeseries_task/sub-03_FD.txt
resources/ex_timeseries_task/sub-03_FD_run_03.txt
resources/ex_timeseries_task/sub-03_FD_run_07.txt
resources/ex_timeseries_task/sub-03_task-heatpainwithregulationandratings_run-01_events.tsv
resources/ex_timeseries_task/sub-03_task-heatpainwithregulationandratings_run-03_events.tsv
resources/ex_timeseries_task/sub-03_task-heatpainwithregulationandratings_run-07_events.tsv
resources/ex_timeseries_task/sub-03_ts.txt
resources/ex_timeseries_task/sub-03_ts_run_03.tsv
connattractor-0.1.0.dist-info/LICENSE
connattractor-0.1.0.dist-info/METADATA
connattractor-0.1.0.dist-info/WHEEL
connattractor-0.1.0.dist-info/RECORD
