Metadata-Version: 2.1
Name: connattractor
Version: 0.1.0
Summary: Tool for analyzing fMRI data with functional connectome-based Hopfield networks (fcHNN)
Home-page: https://pni-lab.github.io/connattractor/
License: GPL-3.0-or-later
Keywords: functional connectivity analysis,brain dynamics,dynamic modelling,brain states,fcHNN,functional connectome,Hopfield
Author: Tamas Spisak
Author-email: tamas.spisak@uni-due.de
Requires-Python: >=3.7
Classifier: License :: OSI Approved :: GNU General Public License v3 or later (GPLv3+)
Classifier: Programming Language :: Python :: 3
Classifier: Programming Language :: Python :: 3.7
Classifier: Programming Language :: Python :: 3.8
Classifier: Programming Language :: Python :: 3.9
Classifier: Programming Language :: Python :: 3.10
Classifier: Programming Language :: Python :: 3.11
Classifier: Programming Language :: Python :: 3.12
Requires-Dist: joblib (>=1.0.1)
Requires-Dist: matplotlib (>=3.5.2)
Requires-Dist: nilearn (>=0.9.1)
Requires-Dist: numpy (>=1.21.1)
Requires-Dist: pandas (>=1.3.1)
Requires-Dist: pingouin (>=0.5.3)
Requires-Dist: scikit-learn (>=1.3)
Requires-Dist: scipy (>=1.7.1)
Requires-Dist: seaborn (>=0.11.1)
Requires-Dist: statsmodels (>=0.12.2)
Requires-Dist: tqdm (>=4.62.0)
Project-URL: Repository, https://github.com/pni-lab/connattractor
